[
  {
    "Filename": "1.png",
    "lines":[
      [
        71,
        479,
        1753,
        446
      ],
      [ 69,
        1018,
        1771,
        1001
      ]
    ],
    "height":1536,
    "width":2048
  },
  {
    "Filename": "1_0(1).png",
    "lines":[
      [
        13,
        446,
        0,
        0
      ],
      [ 0,
      	0,
        0,
        0
      ]
    ],
    "height":1536,
    "width":2048
  },
  {
    "Filename": "1_0(2).png",
    "lines":[
      [
        11,
        440,
        0,
        0
      ],
      [ 0,
        0,
        0,
        0
      ]
    ],
    "height":1536,
    "width":2048
  },
  {
    "Filename": "3.png",
    "lines":[
      [
        183,
        463,
        1871,
        474
      ],
      [ 176,
        1028,
        1884,
        1017
      ]
    ],
     "height":1536,
    "width":2048
  },
  {
    "Filename": "4.png",
    "lines":[
      [
        412,
	638,
	1633,
	700
      ],
      [ 412,
	1085,
	1628,
	1098
      ]
    ],
  "height":1536,
    "width":2048
  },
  {
    "Filename": "5.png",
    "lines":[
      [
        533,
	699,
	1499,
	690
      ],
      [ 534,
	1008,
	1503,
	1002
      ]
    ],
  "height":1536,
    "width":2048
  },
  {
    "Filename": "44cm.png",
    "lines":[
      [
        461,
	577,
	1606,
	590
      ],
      [ 69,
      1018,
      1771,
      1001
      ]
    ],
  "height":1536,
    "width":2048
  },
  {
    "Filename": "49cm.png",
   "lines":[
      [
        495,
	612,
	1520,
	605
      ],
      [ 499,
	944,
	1520,
	938
      ]
    ],
   "height":1536,
    "width":2048
  },
  {
    "Filename": "100.png",
    "lines":[
      [
        430,
	607,
	1578,
	598
      ],
      [ 444,
	974,
	1569,
	966
      ]
    ],
  "height":1536,
    "width":2048
  },
  {
    "Filename": "200.png",
    "lines":[
      [
        423,
	712,
	1564,
	719
      ],
      [ 432,
	1077,
	1550,
	1084
      ]
    ],
   "height":1536,
    "width":2048
  },
  {
    "Filename": "bpp_r1.png",
    "lines":[
      [
        398,
	533,
	1629,
	526
      ],
      [ 401,
	932,
	1629,
	931
      ]
    ],
   "height":1536,
    "width":2048
  },
 {
    "Filename": "bpp_v1.png",
    "lines":[
      [
        409,
	567,
	1641,
	556
      ],
      [ 415,
	964,
	1642,
	960
      ]
    ],
   "height":1536,
    "width":2048
  },
  {
    "Filename": "bpp_v2.png",
    "lines":[
      [
        408,
	566,
	1639,
	555
      ],
      [ 414,
	964,
	1640,
	959
      ]
    ],
  "height":1536,
    "width":2048
  },
 {
    "Filename": "Rückseite8_t.png",
    "lines":[
      [
        537,
	424,
	1619,
	422
      ],
      [ 512,
	765,
	1661,
	757
      ]
    ],
   "height":1536,
    "width":2048
  },
  {
    "Filename": "Rückseite10_t.png",
    "lines":[
      [
        469,
	560,
	1585,
	573
      ],
      [ 432,
	915,
	1619,
	929
      ]
    ],
   "height":1536,
    "width":2048
  },
  {
    "Filename": "Rückseite11_t.png",
    "lines":[
      [
        437,
	262,
	1647,
	273
      ],
      [ 433,
	664,
	1661,
	660
      ]
    ],
  "height":1536,
    "width":2048
  },
  {
    "Filename": "Rückseite17_t.png",
   "lines":[
      [
        503,
	773,
	1507,
	339
      ],
      [ 643,
	1120,
	1689,
	632
      ]
    ],
  "height":1536,
    "width":2048
  },
  {
    "Filename": "Rückseite19_t.png",
    "lines":[
      [
        500,
	448,
	1587,
	453
      ],
      [ 469,
	788,
	1627,
	795
      ]
    ],
   "height":1536,
    "width":2048
  },
  {
    "Filename": "Rückseite20_t.png",
    "lines":[
      [
        484,
	594,
	1481,
	305
      ],
      [ 552,
	915,
	1619,
	594
      ]
    ],
   "height":1536,
    "width":2048
  },
  {
    "Filename": "Rückseite22_t.png",
    "lines":[
      [
        428,
	597,
	1550,
	526
      ],
      [ 397,
	948,
	1612,
	883
      ]
    ],
   "height":1536,
    "width":2048
  },
  {
    "Filename": "test0.png",
    "lines":[
      [
        115,
	597,
	1962,
	582
      ],
      [ 144,
	1199,
	1943,
	1159
      ]
    ],
 "height":1536,
    "width":2048
  },
  {
    "Filename": "test00.png",
    "lines":[
      [
        107,
	430,
	1967,
	427
      ],
      [ 135,
	1046,
	1946,
	1014
      ]
    ],
   "height":1536,
    "width":2048
  },
  {
    "Filename": "test0000.png",
    "lines":[
      [
        111,
	433,
	1967,
	430
      ],
      [ 1948,
	1014,
	137,
	1046
      ]
    ],
   "height":1536,
    "width":2048
  },
  {
    "Filename": "test1.png",
    "lines":[
      [
        114,
	596,
	1963,
	583
      ],
      [ 143,
	1200,
	1942,
	1157
      ]
    ],
 "height":1536,
    "width":2048
  },
  {
    "Filename": "test2.png",
    "lines":[
      [
        114,
	595,
	1963,
	582
      ],
      [ 145,
	1201,
	1941,
	1201
      ]
    ],
 "height":1536,
    "width":2048
  },
  {
    "Filename": "test10.png",
   "lines":[
      [
        109,
	430,
	1969,
	429
      ],
      [ 1948,
	1011,
	135,
	1045
      ]
    ],
   "height":1536,
    "width":2048
  },
  {
    "Filename": "test40.png",
    "lines":[
      [
        109,
	431,
	1969,
	429
      ],
      [ 137,
	1045,
	1947,
	1012
      ]
    ],
   "height":1536,
    "width":2048
  },
  {
    "Filename": "test1000.png",
    "lines":[
      [
        109,
	432,
	1969,
	430
      ],
      [ 135,
	1045,
	1947,
	1014
      ]
    ],
   "height":1536,
    "width":2048
  },
  {
    "Filename": "test2000.png",
    "lines":[
      [
        108,
	433,
	1969,
	431
      ],
      [ 137,
	1045,
	1947,
	1015
      ]
    ],
   "height":1536,
    "width":2048
  },
  {
    "Filename": "Vorderseite1.png",
    "lines":[
      [
        470,
	671,
	1613,
	697
      ],
      [ 437,
	1056,
	1639,
	1066
      ]
    ],
 "height":1536,
    "width":2048
  },
  { 
    "Filename": "Vorderseite3_t.png",
    "lines":[
      [
        550,
	535,
	1664,
	758
      ],
      [ 450,
	886,
	1621,
	1127
      ]
    ],
   "height":1536,
    "width":2048
  },
  {
    "Filename": "Vorderseite4_t.png",
    "lines":[
      [
        551,
	628,
	1536,
	300
      ],
      [ 621,
	967,
	1687,
	594
      ]
    ],
   "height":1536,
    "width":2048
  },
  {
    "Filename": "Vorderseite5_t.png",
    "lines":[
      [
        550,
	448,
	1642,
	512
      ],
      [ 497,
	793,
	1652,
	857
      ]
    ],
   "height":1536,
    "width":2048
  },
  {
    "Filename": "Vorderseite14_t.png",
   "lines":[
      [
        430,
	349,
	1642,
	350
      ],
      [ 429,
	750,
	1649,
	730
      ]
    ],
   "height":1536,
    "width":2048
  },
  {
    "Filename": "Vorderseite16_t.png",
    "lines":[
      [
        486,
	194,
	1671,
	388
      ],
      [ 412,
	579,
	1617,
	768
      ]
    ],
   "height":1536,
    "width":2048
  },
  {
    "Filename": "Vorderseite19_t.png",
    "lines":[
      [
        390,
	287,
	1380,
	238
      ],
      [ 355,
	581,
	1408,
	531
      ]
    ],
  "height":1536,
    "width":2048
  },
  {
    "Filename": "Vorderseite21_t.png",
    "lines":[
      [
        430,
	629,
	1573,
	640
      ],
      [ 370,
	986,
	1599,
	1011
      ]
    ],
   "height":1536,
    "width":2048
  },
  {
    "Filename": "Vorderseite24_t.png",
    "lines":[
      [
        371,
	807,
	1295,
	304
      ],
      [ 519,
	1120,
	1492,
	554
      ]
    ],
  "height":1536,
    "width":2048
  }
]